{
    "title": "Среднее время наработки на отказ (μ = 1 1/hours, m = 1)",
    "legend": ["λ = 10^-5 1/hours", "λ = 10^-6 1/hours", "λ = 10^-7 1/hours"],
    "xlabel": "Число элементарных машин",
    "ylabel": "Мат. ожидание времени безотказной работы",
    "xdata": [65527, 65528, 65529, 65530, 65531, 65532, 65533, 65534, 65535, 65536],
    "ydata": [
        [
            195.7589,
            127.2749,
            82.4007,
            52.9964,
            33.7285,
            21.1026,
            12.829,
            7.4072,
            3.8542,
            1.5259
        ],
        [
            732717066011.7946,
            48012751183.5548,
            3146179558.556,
            206165999.2926,
            13510056.9336,
            885326.5409,
            58016.2189,
            3800.9769,
            248.0932,
            15.2588
        ],
        [
            6.892146081629684e+21,
            4.516216562909483e+19,
            2.9593863893433254e+17,
            1939256307072786.8,
            12707946580246.97,
            83276444734.0164,
            545727196.631,
            3576313.0377,
            23436.0099,
            152.5879
        ]
    ]
}